yqk_tools/__init__.py
yqk_tools-0.0.2.dist-info/LICENSE
yqk_tools-0.0.2.dist-info/METADATA
yqk_tools-0.0.2.dist-info/WHEEL
yqk_tools-0.0.2.dist-info/top_level.txt
yqk_tools-0.0.2.dist-info/RECORD
