Metadata-Version: 2.1
Name: yqk-tools
Version: 0.0.2
Summary: yqk's tools
Home-page: https://github.com/yqkcn/yqk-tools
Author: yqk
Author-email: 410728991@qq.com
License: UNKNOWN
Project-URL: Bug Tracker, https://github.com/yqkcn/yqk-tools/issues
Platform: UNKNOWN
Classifier: Programming Language :: Python :: 3
Classifier: License :: OSI Approved :: MIT License
Classifier: Operating System :: OS Independent
Requires-Python: >=3.6
